twitterUsernameviaUserID/__init__.py
twitterUsernameviaUserID/__version__.py
twitterUsernameviaUserID/getHandles.py
twitterUsernameviaUserID-0.0.4.dist-info/LICENSE
twitterUsernameviaUserID-0.0.4.dist-info/METADATA
twitterUsernameviaUserID-0.0.4.dist-info/WHEEL
twitterUsernameviaUserID-0.0.4.dist-info/top_level.txt
twitterUsernameviaUserID-0.0.4.dist-info/RECORD
