Metadata-Version: 2.1
Name: twitterUsernameviaUserID
Version: 0.0.4
Summary: An advanced Twitter scraping tool. No authentication. No API. No limits to fetching usernames from the user id's.
Home-page: https://github.com/rishi-raj-jain/twitterUsernamefromUserID
Author: Rishi Raj Jain, Dvanne laine, Devansh Srivastav
Author-email: rishi18304@iiitd.ac.in
License: MIT
Platform: UNKNOWN
Classifier: Programming Language :: Python :: 3
Classifier: License :: OSI Approved :: MIT License
Classifier: Operating System :: OS Independent
Requires-Python: >=3.6.0
Requires-Dist: selenium
Requires-Dist: webdriver-manager
Requires-Dist: twitterUsernameviaUserID
